{"nodes": [{"id": "home_tuxed_nimbox_sre_app_report_builder_py", "label": "report_builder.py", "file_type": "code", "source_file": "app/report_builder.py", "source_location": "L1"}, {"id": "home_tuxed_nimbox_sre_app_report_builder_load_report_script", "label": "_load_report_script()", "file_type": "code", "source_file": "app/report_builder.py", "source_location": "L15", "_callable": true}, {"id": "home_tuxed_nimbox_sre_app_report_builder_annualize", "label": "_annualize()", "file_type": "code", "source_file": "app/report_builder.py", "source_location": "L23", "_callable": true}, {"id": "home_tuxed_nimbox_sre_app_report_builder_normalize_tariff", "label": "_normalize_tariff()", "file_type": "code", "source_file": "app/report_builder.py", "source_location": "L30", "_callable": true}, {"id": "home_tuxed_nimbox_sre_app_report_builder_map_consumption_for_report", "label": "_map_consumption_for_report()", "file_type": "code", "source_file": "app/report_builder.py", "source_location": "L34", "_callable": true}, {"id": "home_tuxed_nimbox_sre_app_report_builder_map_power_for_report", "label": "_map_power_for_report()", "file_type": "code", "source_file": "app/report_builder.py", "source_location": "L43", "_callable": true}, {"id": "home_tuxed_nimbox_sre_app_report_builder_build_report_payload", "label": "build_report_payload()", "file_type": "code", "source_file": "app/report_builder.py", "source_location": "L52", "_callable": true}, {"id": "analysiscontext", "label": "AnalysisContext", "file_type": "code", "source_file": "", "source_location": "", "origin_file": "/home/tuxed/nimbox-sre/app/report_builder.py"}, {"id": "any", "label": "Any", "file_type": "code", "source_file": "", "source_location": "", "origin_file": "/home/tuxed/nimbox-sre/app/report_builder.py"}, {"id": "home_tuxed_nimbox_sre_app_report_builder_generate_report_pdf", "label": "generate_report_pdf()", "file_type": "code", "source_file": "app/report_builder.py", "source_location": "L152", "_callable": true}, {"id": "path", "label": "Path", "file_type": "code", "source_file": "", "source_location": "", "origin_file": "/home/tuxed/nimbox-sre/app/report_builder.py"}, {"id": "home_tuxed_nimbox_sre_app_report_builder_save_report_payload", "label": "save_report_payload()", "file_type": "code", "source_file": "app/report_builder.py", "source_location": "L161", "_callable": true}], "edges": [{"source": "home_tuxed_nimbox_sre_app_report_builder_py", "target": "importlib_util", "relation": "imports", "context": "import", "confidence": "EXTRACTED", "source_file": "app/report_builder.py", "source_location": "L3", "weight": 1.0}, {"source": "home_tuxed_nimbox_sre_app_report_builder_py", "target": "json", "relation": "imports", "context": "import", "confidence": "EXTRACTED", "source_file": "app/report_builder.py", "source_location": "L4", "weight": 1.0}, {"source": "home_tuxed_nimbox_sre_app_report_builder_py", "target": "datetime", "relation": "imports_from", "context": "import", "confidence": "EXTRACTED", "source_file": "app/report_builder.py", "source_location": "L5", "weight": 1.0}, {"source": "home_tuxed_nimbox_sre_app_report_builder_py", "target": "pathlib", "relation": "imports_from", "context": "import", "confidence": "EXTRACTED", "source_file": "app/report_builder.py", "source_location": "L6", "weight": 1.0}, {"source": "home_tuxed_nimbox_sre_app_report_builder_py", "target": "typing", "relation": "imports_from", "context": "import", "confidence": "EXTRACTED", "source_file": "app/report_builder.py", "source_location": "L7", "weight": 1.0}, {"source": "home_tuxed_nimbox_sre_app_report_builder_py", "target": "home_tuxed_nimbox_sre_app_models_py", "relation": "imports_from", "context": "import", "confidence": "EXTRACTED", "source_file": "app/report_builder.py", "source_location": "L9", "weight": 1.0}, {"source": "home_tuxed_nimbox_sre_app_report_builder_py", "target": "home_tuxed_nimbox_sre_app_report_builder_load_report_script", "relation": "contains", "confidence": "EXTRACTED", "source_file": "app/report_builder.py", "source_location": "L15", "weight": 1.0}, {"source": "home_tuxed_nimbox_sre_app_report_builder_py", "target": "home_tuxed_nimbox_sre_app_report_builder_annualize", "relation": "contains", "confidence": "EXTRACTED", "source_file": "app/report_builder.py", "source_location": "L23", "weight": 1.0}, {"source": "home_tuxed_nimbox_sre_app_report_builder_py", "target": "home_tuxed_nimbox_sre_app_report_builder_normalize_tariff", "relation": "contains", "confidence": "EXTRACTED", "source_file": "app/report_builder.py", "source_location": "L30", "weight": 1.0}, {"source": "home_tuxed_nimbox_sre_app_report_builder_py", "target": "home_tuxed_nimbox_sre_app_report_builder_map_consumption_for_report", "relation": "contains", "confidence": "EXTRACTED", "source_file": "app/report_builder.py", "source_location": "L34", "weight": 1.0}, {"source": "home_tuxed_nimbox_sre_app_report_builder_py", "target": "home_tuxed_nimbox_sre_app_report_builder_map_power_for_report", "relation": "contains", "confidence": "EXTRACTED", "source_file": "app/report_builder.py", "source_location": "L43", "weight": 1.0}, {"source": "home_tuxed_nimbox_sre_app_report_builder_py", "target": "home_tuxed_nimbox_sre_app_report_builder_build_report_payload", "relation": "contains", "confidence": "EXTRACTED", "source_file": "app/report_builder.py", "source_location": "L52", "weight": 1.0}, {"source": "home_tuxed_nimbox_sre_app_report_builder_build_report_payload", "target": "analysiscontext", "relation": "references", "context": "parameter_type", "confidence": "EXTRACTED", "source_file": "app/report_builder.py", "source_location": "L52", "weight": 1.0}, {"source": "home_tuxed_nimbox_sre_app_report_builder_build_report_payload", "target": "any", "relation": "references", "context": "generic_arg", "confidence": "EXTRACTED", "source_file": "app/report_builder.py", "source_location": "L52", "weight": 1.0}, {"source": "home_tuxed_nimbox_sre_app_report_builder_py", "target": "home_tuxed_nimbox_sre_app_report_builder_generate_report_pdf", "relation": "contains", "confidence": "EXTRACTED", "source_file": "app/report_builder.py", "source_location": "L152", "weight": 1.0}, {"source": "home_tuxed_nimbox_sre_app_report_builder_generate_report_pdf", "target": "analysiscontext", "relation": "references", "context": "parameter_type", "confidence": "EXTRACTED", "source_file": "app/report_builder.py", "source_location": "L152", "weight": 1.0}, {"source": "home_tuxed_nimbox_sre_app_report_builder_generate_report_pdf", "target": "path", "relation": "references", "context": "parameter_type", "confidence": "EXTRACTED", "source_file": "app/report_builder.py", "source_location": "L152", "weight": 1.0}, {"source": "home_tuxed_nimbox_sre_app_report_builder_generate_report_pdf", "target": "path", "relation": "references", "context": "generic_arg", "confidence": "EXTRACTED", "source_file": "app/report_builder.py", "source_location": "L152", "weight": 1.0}, {"source": "home_tuxed_nimbox_sre_app_report_builder_generate_report_pdf", "target": "any", "relation": "references", "context": "generic_arg", "confidence": "EXTRACTED", "source_file": "app/report_builder.py", "source_location": "L152", "weight": 1.0}, {"source": "home_tuxed_nimbox_sre_app_report_builder_py", "target": "home_tuxed_nimbox_sre_app_report_builder_save_report_payload", "relation": "contains", "confidence": "EXTRACTED", "source_file": "app/report_builder.py", "source_location": "L161", "weight": 1.0}, {"source": "home_tuxed_nimbox_sre_app_report_builder_save_report_payload", "target": "any", "relation": "references", "context": "generic_arg", "confidence": "EXTRACTED", "source_file": "app/report_builder.py", "source_location": "L161", "weight": 1.0}, {"source": "home_tuxed_nimbox_sre_app_report_builder_save_report_payload", "target": "path", "relation": "references", "context": "parameter_type", "confidence": "EXTRACTED", "source_file": "app/report_builder.py", "source_location": "L161", "weight": 1.0}, {"source": "home_tuxed_nimbox_sre_app_report_builder_save_report_payload", "target": "path", "relation": "references", "context": "return_type", "confidence": "EXTRACTED", "source_file": "app/report_builder.py", "source_location": "L161", "weight": 1.0}, {"source": "home_tuxed_nimbox_sre_app_report_builder_build_report_payload", "target": "home_tuxed_nimbox_sre_app_report_builder_normalize_tariff", "relation": "calls", "context": "call", "confidence": "EXTRACTED", "source_file": "app/report_builder.py", "source_location": "L63", "weight": 1.0}, {"source": "home_tuxed_nimbox_sre_app_report_builder_build_report_payload", "target": "home_tuxed_nimbox_sre_app_report_builder_annualize", "relation": "calls", "context": "call", "confidence": "EXTRACTED", "source_file": "app/report_builder.py", "source_location": "L69", "weight": 1.0}, {"source": "home_tuxed_nimbox_sre_app_report_builder_build_report_payload", "target": "home_tuxed_nimbox_sre_app_report_builder_map_consumption_for_report", "relation": "calls", "context": "call", "confidence": "EXTRACTED", "source_file": "app/report_builder.py", "source_location": "L91", "weight": 1.0}, {"source": "home_tuxed_nimbox_sre_app_report_builder_build_report_payload", "target": "home_tuxed_nimbox_sre_app_report_builder_map_power_for_report", "relation": "calls", "context": "call", "confidence": "EXTRACTED", "source_file": "app/report_builder.py", "source_location": "L101", "weight": 1.0}, {"source": "home_tuxed_nimbox_sre_app_report_builder_generate_report_pdf", "target": "home_tuxed_nimbox_sre_app_report_builder_load_report_script", "relation": "calls", "context": "call", "confidence": "EXTRACTED", "source_file": "app/report_builder.py", "source_location": "L153", "weight": 1.0}, {"source": "home_tuxed_nimbox_sre_app_report_builder_generate_report_pdf", "target": "home_tuxed_nimbox_sre_app_report_builder_build_report_payload", "relation": "calls", "context": "call", "confidence": "EXTRACTED", "source_file": "app/report_builder.py", "source_location": "L154", "weight": 1.0}], "raw_calls": [{"caller_nid": "home_tuxed_nimbox_sre_app_report_builder_load_report_script", "callee": "spec_from_file_location", "is_member_call": true, "source_file": "app/report_builder.py", "source_location": "L16", "receiver": null}, {"caller_nid": "home_tuxed_nimbox_sre_app_report_builder_load_report_script", "callee": "SCRIPT_PATH", "is_member_call": false, "indirect": true, "context": "argument", "source_file": "app/report_builder.py", "source_location": "L16"}, {"caller_nid": "home_tuxed_nimbox_sre_app_report_builder_load_report_script", "callee": "module_from_spec", "is_member_call": true, "source_file": "app/report_builder.py", "source_location": "L17", "receiver": null}, {"caller_nid": "home_tuxed_nimbox_sre_app_report_builder_load_report_script", "callee": "exec_module", "is_member_call": true, "source_file": "app/report_builder.py", "source_location": "L19", "receiver": null}, {"caller_nid": "home_tuxed_nimbox_sre_app_report_builder_normalize_tariff", "callee": "replace", "is_member_call": true, "source_file": "app/report_builder.py", "source_location": "L31", "receiver": null}, {"caller_nid": "home_tuxed_nimbox_sre_app_report_builder_map_consumption_for_report", "callee": "get", "is_member_call": true, "source_file": "app/report_builder.py", "source_location": "L37", "receiver": "periods"}, {"caller_nid": "home_tuxed_nimbox_sre_app_report_builder_map_consumption_for_report", "callee": "get", "is_member_call": true, "source_file": "app/report_builder.py", "source_location": "L37", "receiver": "periods"}, {"caller_nid": "home_tuxed_nimbox_sre_app_report_builder_map_consumption_for_report", "callee": "get", "is_member_call": true, "source_file": "app/report_builder.py", "source_location": "L38", "receiver": "periods"}, {"caller_nid": "home_tuxed_nimbox_sre_app_report_builder_map_consumption_for_report", "callee": "get", "is_member_call": true, "source_file": "app/report_builder.py", "source_location": "L40", "receiver": "periods"}, {"caller_nid": "home_tuxed_nimbox_sre_app_report_builder_map_power_for_report", "callee": "get", "is_member_call": true, "source_file": "app/report_builder.py", "source_location": "L46", "receiver": "periods"}, {"caller_nid": "home_tuxed_nimbox_sre_app_report_builder_map_power_for_report", "callee": "get", "is_member_call": true, "source_file": "app/report_builder.py", "source_location": "L46", "receiver": "periods"}, {"caller_nid": "home_tuxed_nimbox_sre_app_report_builder_map_power_for_report", "callee": "get", "is_member_call": true, "source_file": "app/report_builder.py", "source_location": "L47", "receiver": "periods"}, {"caller_nid": "home_tuxed_nimbox_sre_app_report_builder_map_power_for_report", "callee": "get", "is_member_call": true, "source_file": "app/report_builder.py", "source_location": "L47", "receiver": "periods"}, {"caller_nid": "home_tuxed_nimbox_sre_app_report_builder_map_power_for_report", "callee": "get", "is_member_call": true, "source_file": "app/report_builder.py", "source_location": "L49", "receiver": "periods"}, {"caller_nid": "home_tuxed_nimbox_sre_app_report_builder_build_report_payload", "callee": "ValueError", "is_member_call": false, "source_file": "app/report_builder.py", "source_location": "L54", "receiver": null}, {"caller_nid": "home_tuxed_nimbox_sre_app_report_builder_build_report_payload", "callee": "get", "is_member_call": true, "source_file": "app/report_builder.py", "source_location": "L131", "receiver": "proposal_power_prices"}, {"caller_nid": "home_tuxed_nimbox_sre_app_report_builder_build_report_payload", "callee": "strftime", "is_member_call": true, "source_file": "app/report_builder.py", "source_location": "L145", "receiver": null}, {"caller_nid": "home_tuxed_nimbox_sre_app_report_builder_build_report_payload", "callee": "today", "is_member_call": true, "source_file": "app/report_builder.py", "source_location": "L145", "receiver": "date"}, {"caller_nid": "home_tuxed_nimbox_sre_app_report_builder_generate_report_pdf", "callee": "mkdir", "is_member_call": true, "source_file": "app/report_builder.py", "source_location": "L155", "receiver": "output_dir"}, {"caller_nid": "home_tuxed_nimbox_sre_app_report_builder_generate_report_pdf", "callee": "build", "is_member_call": true, "source_file": "app/report_builder.py", "source_location": "L157", "receiver": "report_module"}, {"caller_nid": "home_tuxed_nimbox_sre_app_report_builder_save_report_payload", "callee": "mkdir", "is_member_call": true, "source_file": "app/report_builder.py", "source_location": "L162", "receiver": "output_dir"}, {"caller_nid": "home_tuxed_nimbox_sre_app_report_builder_save_report_payload", "callee": "write_text", "is_member_call": true, "source_file": "app/report_builder.py", "source_location": "L164", "receiver": "path"}, {"caller_nid": "home_tuxed_nimbox_sre_app_report_builder_save_report_payload", "callee": "dumps", "is_member_call": true, "source_file": "app/report_builder.py", "source_location": "L164", "receiver": "json"}]}